swordserver/__init__.py
swordserver/auth.py
swordserver/controller.py
swordserver/libs.py
swordserver/main.py
swordserver/manifest.py
swordserver/model.py
swordserver/setting.py
swordserver/telerobot.py
swordserver/ui.py
swordserver/__pycache__/controller.cpython-36.pyc
swordserver/__pycache__/setting.cpython-36.pyc
swordserver/__pycache__/ui.cpython-36.pyc
swordserver/static/bootstrap/dist/css/bootstrap-theme.css
swordserver/static/bootstrap/dist/css/bootstrap-theme.css.map
swordserver/static/bootstrap/dist/css/bootstrap-theme.min.css
swordserver/static/bootstrap/dist/css/bootstrap.css
swordserver/static/bootstrap/dist/css/bootstrap.css.map
swordserver/static/bootstrap/dist/css/bootstrap.min.css
swordserver/static/bootstrap/dist/js/bootstrap.js
swordserver/static/bootstrap/dist/js/bootstrap.min.js
swordserver/static/bootstrap/grunt/bs-glyphicons-data-generator.js
swordserver/static/bootstrap/grunt/bs-lessdoc-parser.js
swordserver/static/bootstrap/grunt/bs-raw-files-generator.js
swordserver/static/bootstrap/grunt/sauce_browsers.yml
swordserver/static/bootstrap/js/affix.js
swordserver/static/bootstrap/js/alert.js
swordserver/static/bootstrap/js/button.js
swordserver/static/bootstrap/js/carousel.js
swordserver/static/bootstrap/js/collapse.js
swordserver/static/bootstrap/js/dropdown.js
swordserver/static/bootstrap/js/modal.js
swordserver/static/bootstrap/js/popover.js
swordserver/static/bootstrap/js/scrollspy.js
swordserver/static/bootstrap/js/tab.js
swordserver/static/bootstrap/js/tooltip.js
swordserver/static/bootstrap/js/transition.js
swordserver/static/bootstrap/less/alerts.less
swordserver/static/bootstrap/less/badges.less
swordserver/static/bootstrap/less/bootstrap.less
swordserver/static/bootstrap/less/breadcrumbs.less
swordserver/static/bootstrap/less/button-groups.less
swordserver/static/bootstrap/less/buttons.less
swordserver/static/bootstrap/less/carousel.less
swordserver/static/bootstrap/less/close.less
x_mroy_1052-0.1.5.dist-info/DESCRIPTION.rst
x_mroy_1052-0.1.5.dist-info/METADATA
x_mroy_1052-0.1.5.dist-info/RECORD
x_mroy_1052-0.1.5.dist-info/WHEEL
x_mroy_1052-0.1.5.dist-info/entry_points.txt
x_mroy_1052-0.1.5.dist-info/metadata.json
x_mroy_1052-0.1.5.dist-info/top_level.txt
