Metadata-Version: 2.0
Name: x-mroy-1052
Version: 0.1.5
Summary: a anayzer package
Home-page: https://github.com/Qingluan/.git
Author: Qing luan
Author-email: UNKNOWN
License: MIT
Platform: UNKNOWN
Requires-Dist: mroylib-min
Requires-Dist: x-mroy-1045
Requires-Dist: qtornado
